upsilonconf/__init__.py
upsilonconf/config.py
upsilonconf/io/__init__.py
upsilonconf/io/_optional_dependencies.py
upsilonconf/io/base.py
upsilonconf/io/cli.py
upsilonconf/io/directory.py
upsilonconf/io/json.py
upsilonconf/io/toml.py
upsilonconf/io/yaml.py
upsilonconf-0.7.0.dist-info/LICENSE
upsilonconf-0.7.0.dist-info/METADATA
upsilonconf-0.7.0.dist-info/WHEEL
upsilonconf-0.7.0.dist-info/top_level.txt
upsilonconf-0.7.0.dist-info/RECORD
