Metadata-Version: 2.1
Name: upsilonconf
Version: 0.7.0
Summary: A simple configuration library
Home-page: https://github.com/hoedt/upsilonconf
Author: Pieter-Jan Hoedt
Author-email: hoedt@ml.jku.at
Project-URL: Documentation, https://hoedt.github.io/upsilonconf
Project-URL: Bug Tracker, https://github.com/hoedt/upsilonconf/issues
Classifier: Development Status :: 3 - Alpha
Classifier: Intended Audience :: Developers
Classifier: Intended Audience :: Science/Research
Classifier: Topic :: Utilities
Classifier: Programming Language :: Python :: 3
Classifier: License :: OSI Approved :: MIT License
Classifier: Operating System :: OS Independent
License-File: LICENSE
Provides-Extra: docs
Requires-Dist: numpydoc (>=1.5.0) ; extra == 'docs'
Provides-Extra: toml
Requires-Dist: tomlkit (>=0.8.0) ; extra == 'toml'
Provides-Extra: yaml
Requires-Dist: pyyaml (>=5.4.1) ; extra == 'yaml'
